bearalpha/__init__.py
bearalpha/__main__.py
bearalpha/core/__init__.py
bearalpha/core/crawl.py
bearalpha/core/database.py
bearalpha/core/quool.py
bearalpha/crawl/__init__.py
bearalpha/crawl/ak.py
bearalpha/crawl/akshare.py
bearalpha/crawl/em.py
bearalpha/crawl/stockus.py
bearalpha/crawl/tushare.py
bearalpha/database/__init__.py
bearalpha/database/__main__.py
bearalpha/database/akshare.py
bearalpha/database/em.py
bearalpha/database/local.py
bearalpha/database/provider.py
bearalpha/database/stockus.py
bearalpha/database/tushare.py
bearalpha/database/staff/__init__.py
bearalpha/database/staff/akshare.py
bearalpha/database/staff/em.py
bearalpha/database/staff/local.py
bearalpha/database/staff/provider.py
bearalpha/database/staff/stockus.py
bearalpha/database/staff/tushare.py
bearalpha/database/tools/__init__.py
bearalpha/database/tools/core.py
bearalpha/quool/__init__.py
bearalpha/quool/__main__.py
bearalpha/quool/analyst.py
bearalpha/quool/artist.py
bearalpha/quool/backtester.py
bearalpha/quool/calculator.py
bearalpha/quool/evaluator.py
bearalpha/quool/fetcher.py
bearalpha/quool/processor.py
bearalpha/quool/staff/__init__.py
bearalpha/quool/staff/analyst.py
bearalpha/quool/staff/artist.py
bearalpha/quool/staff/backtester.py
bearalpha/quool/staff/calculator.py
bearalpha/quool/staff/evaluator.py
bearalpha/quool/staff/fetcher.py
bearalpha/quool/staff/processor.py
bearalpha/quool/tools/__init__.py
bearalpha/quool/tools/cli.py
bearalpha/quool/tools/common.py
bearalpha/quool/tools/core.py
bearalpha/quool/tools/io.py
bearalpha/tools/__init__.py
bearalpha/tools/common.py
bearalpha/tools/io.py
factor/__init__.py
factor/__main__.py
factor/barrastyle/__init__.py
factor/barrastyle/growth.py
factor/barrastyle/leverage.py
factor/barrastyle/liquidity.py
factor/barrastyle/pricevolume.py
factor/barrastyle/quality.py
factor/barrastyle/size.py
factor/barrastyle/technical.py
factor/barrastyle/turnover.py
factor/barrastyle/valuation.py
factor/barrastyle/volatility.py
bearalpha-0.1.4.dist-info/METADATA
bearalpha-0.1.4.dist-info/WHEEL
bearalpha-0.1.4.dist-info/entry_points.txt
bearalpha-0.1.4.dist-info/top_level.txt
bearalpha-0.1.4.dist-info/RECORD
