Metadata-Version: 2.1
Name: bearalpha
Version: 0.1.4
Summary: A Quantum Finance Analyze Toolkit
Home-page: https://github.com/ppoak/BearAlpha
Author: ppoak
Author-email: ppoak@foxmail.com
License: UNKNOWN
Keywords: Quantum,Finance
Platform: UNKNOWN
Requires-Dist: pandas
Requires-Dist: numpy
Requires-Dist: matplotlib
Requires-Dist: mplfinance
Requires-Dist: backtrader
Requires-Dist: sqlalchemy
Requires-Dist: diskcache
Requires-Dist: requests
Requires-Dist: rich
Requires-Dist: scipy
Requires-Dist: bs4
